<?xml version="1.0" encoding="UTF-8"?>
<operation id="1f972b40-7345-4579-85de-2514d00e5096">
  <descriptionCdata><![CDATA[1f972b40-7345-4579-85de-2514d00e5096.description=This will run whatever command line is passed to it in the background \n\nInputs\:\n\nhost\:  the system to check\nusername\: the user to log into this system as\npassword\: the password to log in with\nservice\: name of the application to run\n\nResponses\:\n\nsuccess\: the data was obtained\nfailure\: the data could not be obtained\n\nResults\: \n\nthe return code\n\n
]]></descriptionCdata>
  <annotation>1f972b40-7345-4579-85de-2514d00e5096.description</annotation>
  <name>Run Service</name>
  <categories/>
  <inputs>
    <userInputBinding id="61335710-78f9-4960-b9eb-f2bdecbd8df2">
      <annotation></annotation>
      <assignFromContext>true</assignFromContext>
      <assignToContext>true</assignToContext>
      <inputType>STRING</inputType>
      <isList>false</isList>
      <required>true</required>
      <isPersisted>true</isPersisted>
      <inputSymbol>host</inputSymbol>
      <listDelimiter>,</listDelimiter>
      <record>false</record>
      <prompt></prompt>
      <isMultiSelect>false</isMultiSelect>
      <sourceDelimiter>|</sourceDelimiter>
    </userInputBinding>
    <userInputBinding id="f60b4388-4aed-4347-a402-ada94cf88854">
      <annotation></annotation>
      <assignFromContext>true</assignFromContext>
      <assignToContext>true</assignToContext>
      <inputType>STRING</inputType>
      <isList>false</isList>
      <required>true</required>
      <isPersisted>true</isPersisted>
      <inputSymbol>username</inputSymbol>
      <listDelimiter>,</listDelimiter>
      <record>false</record>
      <prompt></prompt>
      <isMultiSelect>false</isMultiSelect>
      <sourceDelimiter>|</sourceDelimiter>
    </userInputBinding>
    <userInputBinding id="2c8ced42-2108-472b-a1c5-48fb46b647d4">
      <annotation></annotation>
      <assignFromContext>true</assignFromContext>
      <assignToContext>true</assignToContext>
      <inputType>ENCRYPTED</inputType>
      <isList>false</isList>
      <required>true</required>
      <isPersisted>true</isPersisted>
      <inputSymbol>password</inputSymbol>
      <listDelimiter>,</listDelimiter>
      <record>false</record>
      <prompt></prompt>
      <isMultiSelect>false</isMultiSelect>
      <sourceDelimiter>|</sourceDelimiter>
    </userInputBinding>
    <userInputBinding id="4e7eed60-1c30-43e3-8442-4ac95163be7f">
      <annotation></annotation>
      <assignFromContext>true</assignFromContext>
      <assignToContext>true</assignToContext>
      <inputType>STRING</inputType>
      <isList>false</isList>
      <required>true</required>
      <isPersisted>true</isPersisted>
      <inputSymbol>service</inputSymbol>
      <listDelimiter>,</listDelimiter>
      <record>false</record>
      <prompt></prompt>
      <isMultiSelect>false</isMultiSelect>
      <sourceDelimiter>|</sourceDelimiter>
    </userInputBinding>
    <userInputBinding id="46a0fef6-bcd0-451f-99c5-dc3ead28bf7d">
      <annotation></annotation>
      <toContextKey></toContextKey>
      <assignFromContext>false</assignFromContext>
      <assignToContext>false</assignToContext>
      <inputType>STRING</inputType>
      <recordKey></recordKey>
      <isList>false</isList>
      <required>false</required>
      <isPersisted>true</isPersisted>
      <inputSymbol>Environment</inputSymbol>
      <listDelimiter></listDelimiter>
      <record>false</record>
      <prompt></prompt>
      <isMultiSelect>false</isMultiSelect>
      <sourceDelimiter>|</sourceDelimiter>
    </userInputBinding>
    <staticBinding id="e7e9d62d-8f93-4690-816c-f0279fed39d1">
      <annotation></annotation>
      <toContextKey></toContextKey>
      <fromContextKey></fromContextKey>
      <assignFromContext>false</assignFromContext>
      <assignToContext>false</assignToContext>
      <inputType>STRING</inputType>
      <recordKey></recordKey>
      <isList>false</isList>
      <required>true</required>
      <isPersisted>true</isPersisted>
      <inputSymbol>Command</inputSymbol>
      <listDelimiter></listDelimiter>
      <value>service ${service} start</value>
      <record>false</record>
    </staticBinding>
    <staticBinding id="713ad906-6047-40e0-be73-cb57e081e8a5">
      <annotation></annotation>
      <toContextKey></toContextKey>
      <fromContextKey></fromContextKey>
      <assignFromContext>false</assignFromContext>
      <assignToContext>false</assignToContext>
      <inputType>STRING</inputType>
      <recordKey></recordKey>
      <isList>false</isList>
      <required>false</required>
      <isPersisted>true</isPersisted>
      <inputSymbol>User</inputSymbol>
      <listDelimiter></listDelimiter>
      <value>${username}</value>
      <record>false</record>
    </staticBinding>
    <userInputBinding id="876e2f65-0f5f-4012-8dde-0f443fee89cb">
      <annotation></annotation>
      <toContextKey></toContextKey>
      <assignFromContext>false</assignFromContext>
      <assignToContext>false</assignToContext>
      <inputType>STRING</inputType>
      <recordKey></recordKey>
      <isList>false</isList>
      <required>false</required>
      <isPersisted>true</isPersisted>
      <inputSymbol>Argument</inputSymbol>
      <listDelimiter></listDelimiter>
      <record>false</record>
      <prompt></prompt>
      <isMultiSelect>false</isMultiSelect>
      <sourceDelimiter>|</sourceDelimiter>
    </userInputBinding>
    <staticBinding id="49a48f29-3797-4ffd-8fef-0b6b16ad2ea8">
      <annotation></annotation>
      <toContextKey></toContextKey>
      <fromContextKey></fromContextKey>
      <assignFromContext>false</assignFromContext>
      <assignToContext>false</assignToContext>
      <inputType>STRING</inputType>
      <recordKey></recordKey>
      <isList>false</isList>
      <required>false</required>
      <isPersisted>true</isPersisted>
      <inputSymbol>Host</inputSymbol>
      <listDelimiter></listDelimiter>
      <value>${host}</value>
      <record>false</record>
    </staticBinding>
    <userInputBinding id="e99b7655-9ce3-4723-b693-cba6615d7aaf">
      <annotation></annotation>
      <toContextKey></toContextKey>
      <assignFromContext>false</assignFromContext>
      <assignToContext>false</assignToContext>
      <inputType>STRING</inputType>
      <recordKey></recordKey>
      <isList>false</isList>
      <required>false</required>
      <isPersisted>true</isPersisted>
      <inputSymbol>Private_Key_File</inputSymbol>
      <listDelimiter></listDelimiter>
      <record>false</record>
      <prompt></prompt>
      <isMultiSelect>false</isMultiSelect>
      <sourceDelimiter>|</sourceDelimiter>
    </userInputBinding>
    <staticBinding id="d385b508-a646-4090-b259-3310abe19ff2">
      <annotation></annotation>
      <toContextKey></toContextKey>
      <fromContextKey></fromContextKey>
      <assignFromContext>false</assignFromContext>
      <assignToContext>false</assignToContext>
      <inputType>ENCRYPTED</inputType>
      <recordKey></recordKey>
      <isList>false</isList>
      <required>false</required>
      <isPersisted>true</isPersisted>
      <inputSymbol>Password</inputSymbol>
      <listDelimiter></listDelimiter>
      <value>{OBFUSCATED}SqstnSxglAP4D4gm72ILRw==</value>
      <record>false</record>
    </staticBinding>
    <staticBinding id="44d554f8-ea64-4f90-b7a4-97b63a3b5cdb">
      <annotation></annotation>
      <toContextKey></toContextKey>
      <fromContextKey></fromContextKey>
      <assignFromContext>false</assignFromContext>
      <assignToContext>false</assignToContext>
      <inputType>STRING</inputType>
      <recordKey></recordKey>
      <isList>false</isList>
      <required>false</required>
      <isPersisted>true</isPersisted>
      <inputSymbol>Pty</inputSymbol>
      <listDelimiter></listDelimiter>
      <value>true</value>
      <record>false</record>
    </staticBinding>
  </inputs>
  <possibleResponses>
    <opResponse id="0359a8cf-f954-4987-9149-d3dfa1a5ba89">
      <annotation></annotation>
      <name>success</name>
      <isDefault>false</isDefault>
      <onFailure>false</onFailure>
      <type>RESOLVED</type>
      <matchRules>
        <expression id="db6072e1-2319-456b-bd4b-5065506a4085">
          <annotation></annotation>
          <name></name>
          <fieldName>Code</fieldName>
          <sourceType>RAWRESULT</sourceType>
          <compare id="548f296c-44db-4d26-8912-be02a28f9743">
            <annotation></annotation>
            <name>Config Item</name>
            <text>0</text>
            <matchType>=</matchType>
          </compare>
          <filters/>
        </expression>
      </matchRules>
    </opResponse>
    <opResponse id="2ebc53df-f425-4657-ad99-b2092f202d3e">
      <annotation></annotation>
      <name>failure</name>
      <isDefault>true</isDefault>
      <onFailure>true</onFailure>
      <type>ERROR</type>
      <matchRules/>
    </opResponse>
  </possibleResponses>
  <availableResultExpressions/>
  <resultExpression id="a625f6f7-2fae-4d3b-b0aa-00028cd75298">
    <annotation></annotation>
    <name></name>
    <fieldName>Code</fieldName>
    <sourceType>RAWRESULT</sourceType>
    <filters/>
  </resultExpression>
  <iconSpec id="1912c9c6-44ad-405e-826c-f4434993e765">
    <baseIcon>document_pulse.png</baseIcon>
    <basePath>Operating System/</basePath>
    <readOnly>false</readOnly>
    <layers>
      <iconSpec id="a2937864-bba6-4c73-a9cd-13a2edc955ee">
        <baseIcon>start.png</baseIcon>
        <basePath>overlays/</basePath>
        <readOnly>false</readOnly>
        <layers/>
      </iconSpec>
      <iconSpec id="8a2c15a4-5c4e-4881-9d53-ad028cdf12d1">
        <baseIcon>start.png</baseIcon>
        <basePath>Annotations/</basePath>
        <readOnly>false</readOnly>
        <layers/>
      </iconSpec>
    </layers>
  </iconSpec>
  <opRef>
    <refId>46c0f7ea-a981-4ddc-bcaf-d4faed7af0b6</refId>
  </opRef>
  <fieldValues/>
  <groupAliasRef>
    <refId>5233030c-af46-432b-a682-b326ca6bf2ae</refId>
    <refName>RAS_Operator_Path</refName>
  </groupAliasRef>
  <overrideGroupAlias>${overrideJRAS}</overrideGroupAlias>
</operation>