<?xml version="1.0" encoding="UTF-8"?>
<operation id="07180d09-cd39-4efd-a27a-95f8b0cf0e46">
  <descriptionCdata><![CDATA[]]></descriptionCdata>
  <annotation></annotation>
  <name>Compare Server Names (1)</name>
  <categories/>
  <inputs>
    <userInputBinding id="d1bd20e1-5e86-4cf2-9a59-f1c85974ca14">
      <annotation></annotation>
      <toContextKey>servername1</toContextKey>
      <assignFromContext>false</assignFromContext>
      <assignToContext>true</assignToContext>
      <inputType>STRING</inputType>
      <isList>false</isList>
      <required>true</required>
      <isPersisted>true</isPersisted>
      <inputSymbol>serverName1</inputSymbol>
      <listDelimiter>,</listDelimiter>
      <record>false</record>
      <prompt></prompt>
      <isMultiSelect>false</isMultiSelect>
      <sourceDelimiter>|</sourceDelimiter>
    </userInputBinding>
    <userInputBinding id="aa348d3b-4ce3-47cf-a384-dd013a84d20f">
      <annotation></annotation>
      <toContextKey>servername2</toContextKey>
      <assignFromContext>false</assignFromContext>
      <assignToContext>true</assignToContext>
      <inputType>STRING</inputType>
      <isList>false</isList>
      <required>true</required>
      <isPersisted>true</isPersisted>
      <inputSymbol>serverName2</inputSymbol>
      <listDelimiter>,</listDelimiter>
      <record>false</record>
      <prompt></prompt>
      <isMultiSelect>false</isMultiSelect>
      <sourceDelimiter>|</sourceDelimiter>
    </userInputBinding>
    <staticBinding id="f86a0e46-93df-458c-a26d-0eea9a902e53">
      <annotation></annotation>
      <assignFromContext>true</assignFromContext>
      <assignToContext>true</assignToContext>
      <inputType>STRING</inputType>
      <isList>false</isList>
      <required>false</required>
      <isPersisted>true</isPersisted>
      <inputSymbol>dnsServer</inputSymbol>
      <listDelimiter>,</listDelimiter>
      <value></value>
      <record>false</record>
    </staticBinding>
  </inputs>
  <possibleResponses>
    <opResponse id="00e73820-f691-4f6c-aca2-7b94e47cf7ed">
      <annotation></annotation>
      <name>success</name>
      <isDefault>false</isDefault>
      <onFailure>false</onFailure>
      <type>RESOLVED</type>
      <matchRules>
        <expression id="02346a65-60de-4919-b792-677554a0a1db">
          <annotation></annotation>
          <name>returnCode</name>
          <fieldName>returnCode</fieldName>
          <sourceType>RAWRESULT</sourceType>
          <containsEvaluator id="54e8e084-707d-45a7-aba1-a8afe42ab9f7">
            <annotation></annotation>
            <name>Config Item</name>
            <text>1</text>
            <ignoreCase>true</ignoreCase>
            <matchType>EXACT_MATCH</matchType>
          </containsEvaluator>
          <filters/>
        </expression>
      </matchRules>
    </opResponse>
    <opResponse id="790f4b2d-2001-4124-94f5-c3b3fcf297e8">
      <annotation></annotation>
      <name>failure</name>
      <isDefault>true</isDefault>
      <onFailure>true</onFailure>
      <type>ERROR</type>
      <matchRules>
        <expression id="df8d8ecb-918b-41f5-bfdf-5953309474a8">
          <annotation></annotation>
          <name>returnCode</name>
          <fieldName>returnCode</fieldName>
          <sourceType>RAWRESULT</sourceType>
          <containsEvaluator id="71ee6854-4870-4a75-b9ed-63078ee66e7c">
            <annotation></annotation>
            <name>Config Item</name>
            <text>0</text>
            <ignoreCase>true</ignoreCase>
            <matchType>EXACT_MATCH</matchType>
          </containsEvaluator>
          <filters/>
        </expression>
      </matchRules>
    </opResponse>
  </possibleResponses>
  <availableResultExpressions/>
  <resultExpression id="4592acb1-7440-4f73-b6be-4515b3307f99">
    <annotation></annotation>
    <name>returnCode</name>
    <fieldName>ipaddress</fieldName>
    <sourceType>RAWRESULT</sourceType>
    <filters/>
  </resultExpression>
  <iconSpec id="e6982a21-c981-4b2b-92e2-fc1711b0ab17">
    <baseIcon>client_network.png</baseIcon>
    <basePath>Networking/</basePath>
    <readOnly>false</readOnly>
    <layers/>
  </iconSpec>
  <plugin>
    <groupId>com.hp.oo</groupId>
    <artifactId>oo-dotnet-web-actions-plugin</artifactId>
    <version>1.12.1-SNAPSHOT</version>
    <actionName>dotNETWebActions_DNSResolver.CompareServerNames</actionName>
  </plugin>
  <fieldValues/>
  <groupAliasRef>
    <refId>5233030c-af46-432b-a682-b326ca6bf2ae</refId>
    <refName>RAS_Operator_Path</refName>
  </groupAliasRef>
  <overrideGroupAlias>${overrideNRAS}</overrideGroupAlias>
</operation>