<?xml version="1.0" encoding="UTF-8"?>
<operation id="918df439-a75e-4c25-b2bd-17ba7cf72fb1">
  <descriptionCdata><![CDATA[918df439-a75e-4c25-b2bd-17ba7cf72fb1.730531be-b38a-49c9-8626-f67de86899c6.prompt=Enter username
918df439-a75e-4c25-b2bd-17ba7cf72fb1.b5903859-19fa-482f-9d45-aa7bfe9100c4.prompt=Enter password
918df439-a75e-4c25-b2bd-17ba7cf72fb1.description=This gets the total \# of disk errors  \n\nInputs\:\nhostname - The host to get query.\nidentity - the username and password to use when authenticating with hostname.\ndisk - The disk to query.\n\nResults\: The result is the total number of disk errors detected.\n\nResponses\:\n   success if the data was gathered\n   failure if the data could not be obtained.  This is usually due to an incorrect input (hostname, username, or password).\n   
]]></descriptionCdata>
  <annotation>918df439-a75e-4c25-b2bd-17ba7cf72fb1.description</annotation>
  <name>Disk - total errors</name>
  <categories/>
  <inputs>
    <userInputBinding id="8dfb86d7-32c6-481e-9fd0-30f0d3bad780">
      <annotation></annotation>
      <assignFromContext>false</assignFromContext>
      <assignToContext>false</assignToContext>
      <inputType>STRING</inputType>
      <isList>false</isList>
      <required>true</required>
      <isPersisted>true</isPersisted>
      <inputSymbol>hostname</inputSymbol>
      <listDelimiter>,</listDelimiter>
      <record>false</record>
      <prompt></prompt>
      <isMultiSelect>false</isMultiSelect>
      <sourceDelimiter>|</sourceDelimiter>
    </userInputBinding>
    <userInputBinding id="730531be-b38a-49c9-8626-f67de86899c6">
      <annotation></annotation>
      <assignFromContext>false</assignFromContext>
      <assignToContext>false</assignToContext>
      <inputType>ENCRYPTED</inputType>
      <isList>false</isList>
      <required>true</required>
      <isPersisted>true</isPersisted>
      <inputSymbol>identityUsername</inputSymbol>
      <listDelimiter>,</listDelimiter>
      <record>false</record>
      <prompt>918df439-a75e-4c25-b2bd-17ba7cf72fb1.730531be-b38a-49c9-8626-f67de86899c6.prompt</prompt>
      <isMultiSelect>false</isMultiSelect>
      <sourceDelimiter></sourceDelimiter>
    </userInputBinding>
    <userInputBinding id="b5903859-19fa-482f-9d45-aa7bfe9100c4">
      <annotation></annotation>
      <assignFromContext>false</assignFromContext>
      <assignToContext>false</assignToContext>
      <inputType>ENCRYPTED</inputType>
      <isList>false</isList>
      <required>true</required>
      <isPersisted>true</isPersisted>
      <inputSymbol>identityPassword</inputSymbol>
      <listDelimiter>,</listDelimiter>
      <record>false</record>
      <prompt>918df439-a75e-4c25-b2bd-17ba7cf72fb1.b5903859-19fa-482f-9d45-aa7bfe9100c4.prompt</prompt>
      <isMultiSelect>false</isMultiSelect>
      <sourceDelimiter></sourceDelimiter>
    </userInputBinding>
    <userInputBinding id="a21035ca-3f93-44a9-9551-122513a48167">
      <annotation></annotation>
      <assignFromContext>false</assignFromContext>
      <assignToContext>false</assignToContext>
      <inputType>STRING</inputType>
      <isList>false</isList>
      <required>true</required>
      <isPersisted>true</isPersisted>
      <inputSymbol>disk</inputSymbol>
      <listDelimiter>,</listDelimiter>
      <record>false</record>
      <prompt></prompt>
      <isMultiSelect>false</isMultiSelect>
      <sourceDelimiter>|</sourceDelimiter>
    </userInputBinding>
    <userInputBinding id="acdc7a96-50ad-4de0-ba04-84d0ff6e1948">
      <annotation></annotation>
      <toContextKey></toContextKey>
      <assignFromContext>false</assignFromContext>
      <assignToContext>false</assignToContext>
      <inputType>STRING</inputType>
      <recordKey></recordKey>
      <isList>false</isList>
      <required>false</required>
      <isPersisted>true</isPersisted>
      <inputSymbol>Environment</inputSymbol>
      <listDelimiter></listDelimiter>
      <record>false</record>
      <prompt></prompt>
      <isMultiSelect>false</isMultiSelect>
      <sourceDelimiter>|</sourceDelimiter>
    </userInputBinding>
    <staticBinding id="0c5586cf-3c9b-4536-979f-9bbbb49428f3">
      <annotation></annotation>
      <toContextKey></toContextKey>
      <fromContextKey></fromContextKey>
      <assignFromContext>false</assignFromContext>
      <assignToContext>false</assignToContext>
      <inputType>STRING</inputType>
      <recordKey></recordKey>
      <isList>false</isList>
      <required>true</required>
      <isPersisted>true</isPersisted>
      <inputSymbol>Command</inputSymbol>
      <listDelimiter></listDelimiter>
      <value>iostat -xen 2 2 | grep ${disk}</value>
      <record>false</record>
    </staticBinding>
    <staticBinding id="0f1e0c0b-d44e-41f0-b24c-970fda841425">
      <annotation></annotation>
      <toContextKey></toContextKey>
      <fromContextKey></fromContextKey>
      <assignFromContext>false</assignFromContext>
      <assignToContext>false</assignToContext>
      <inputType>STRING</inputType>
      <recordKey></recordKey>
      <isList>false</isList>
      <required>false</required>
      <isPersisted>true</isPersisted>
      <inputSymbol>User</inputSymbol>
      <listDelimiter></listDelimiter>
      <value>${identityUsername}</value>
      <record>false</record>
    </staticBinding>
    <userInputBinding id="48d41c55-c3c5-4e35-a264-715ba5b083e3">
      <annotation></annotation>
      <toContextKey></toContextKey>
      <assignFromContext>false</assignFromContext>
      <assignToContext>false</assignToContext>
      <inputType>STRING</inputType>
      <recordKey></recordKey>
      <isList>false</isList>
      <required>false</required>
      <isPersisted>true</isPersisted>
      <inputSymbol>Argument</inputSymbol>
      <listDelimiter></listDelimiter>
      <record>false</record>
      <prompt></prompt>
      <isMultiSelect>false</isMultiSelect>
      <sourceDelimiter>|</sourceDelimiter>
    </userInputBinding>
    <staticBinding id="fba2738d-8379-43e0-bcf0-f99eb88a8e3c">
      <annotation></annotation>
      <toContextKey></toContextKey>
      <fromContextKey></fromContextKey>
      <assignFromContext>false</assignFromContext>
      <assignToContext>false</assignToContext>
      <inputType>STRING</inputType>
      <recordKey></recordKey>
      <isList>false</isList>
      <required>false</required>
      <isPersisted>true</isPersisted>
      <inputSymbol>Host</inputSymbol>
      <listDelimiter></listDelimiter>
      <value>${hostname}</value>
      <record>false</record>
    </staticBinding>
    <userInputBinding id="ebc38385-b701-41fe-aaee-4a09bbf64711">
      <annotation></annotation>
      <toContextKey></toContextKey>
      <assignFromContext>false</assignFromContext>
      <assignToContext>false</assignToContext>
      <inputType>STRING</inputType>
      <recordKey></recordKey>
      <isList>false</isList>
      <required>false</required>
      <isPersisted>true</isPersisted>
      <inputSymbol>Private_Key_File</inputSymbol>
      <listDelimiter></listDelimiter>
      <record>false</record>
      <prompt></prompt>
      <isMultiSelect>false</isMultiSelect>
      <sourceDelimiter>|</sourceDelimiter>
    </userInputBinding>
    <staticBinding id="a36d90f8-fbc2-4a59-8f95-b56d45ab59aa">
      <annotation></annotation>
      <toContextKey></toContextKey>
      <fromContextKey></fromContextKey>
      <assignFromContext>false</assignFromContext>
      <assignToContext>false</assignToContext>
      <inputType>ENCRYPTED</inputType>
      <recordKey></recordKey>
      <isList>false</isList>
      <required>false</required>
      <isPersisted>true</isPersisted>
      <inputSymbol>Password</inputSymbol>
      <listDelimiter></listDelimiter>
      <value>{OBFUSCATED}US5wnHkQ47E2L9FCXJ5F+T0xXjijbPyz9ZnDWsqUaQ4=</value>
      <record>false</record>
    </staticBinding>
    <staticBinding id="e1103da9-077c-4943-85d0-99ef2467566c">
      <annotation></annotation>
      <toContextKey></toContextKey>
      <fromContextKey></fromContextKey>
      <assignFromContext>false</assignFromContext>
      <assignToContext>false</assignToContext>
      <inputType>STRING</inputType>
      <recordKey></recordKey>
      <isList>false</isList>
      <required>false</required>
      <isPersisted>true</isPersisted>
      <inputSymbol>Pty</inputSymbol>
      <listDelimiter></listDelimiter>
      <value>false</value>
      <record>false</record>
    </staticBinding>
  </inputs>
  <possibleResponses>
    <opResponse id="ad83e2f0-8b6c-499d-a957-19e72ef45b98">
      <annotation></annotation>
      <name>success</name>
      <isDefault>false</isDefault>
      <onFailure>false</onFailure>
      <type>RESOLVED</type>
      <matchRules>
        <expression id="0ca6b9cc-d876-4c7c-b108-11ff0daf1f70">
          <annotation></annotation>
          <name></name>
          <fieldName>Code</fieldName>
          <sourceType>RAWRESULT</sourceType>
          <compare id="8ef5525e-5be6-4757-9de9-5dad7120c8c0">
            <annotation></annotation>
            <name>Config Item</name>
            <text>0</text>
            <matchType>=</matchType>
          </compare>
          <filters/>
        </expression>
      </matchRules>
    </opResponse>
    <opResponse id="89c0e51e-56ed-484b-8fd5-fa68fbef69fc">
      <annotation></annotation>
      <name>failure</name>
      <isDefault>true</isDefault>
      <onFailure>true</onFailure>
      <type>ERROR</type>
      <matchRules/>
    </opResponse>
  </possibleResponses>
  <availableResultExpressions/>
  <resultExpression id="127cdd18-d745-4169-b5c2-d556c4fadb41">
    <annotation></annotation>
    <name></name>
    <fieldName>Output String</fieldName>
    <sourceType>RAWRESULT</sourceType>
    <filters>
      <tableFilter id="ced21406-878d-44a8-a380-f593a7591fdd">
        <annotation></annotation>
        <name>Config Item</name>
        <ascending>false</ascending>
        <columnDelimiter>WHITESPACE</columnDelimiter>
        <firstRowHeader>false</firstRowHeader>
        <lineDelimintor>NEWLINE</lineDelimintor>
        <selectCol>14</selectCol>
        <selectHeight>1</selectHeight>
        <selectRow>0</selectRow>
        <selectWidth>1</selectWidth>
        <sortColumn>0</sortColumn>
        <stripFirstRow>false</stripFirstRow>
      </tableFilter>
      <stripWhitespaceFilter id="97d71394-6f77-4911-9f7e-37b68990945d">
        <annotation></annotation>
        <name>Config Item</name>
      </stripWhitespaceFilter>
    </filters>
  </resultExpression>
  <iconSpec id="ffedb3ce-771f-4200-86e3-d90106cf1028">
    <baseIcon>document_pulse.png</baseIcon>
    <basePath>Operating System/</basePath>
    <readOnly>false</readOnly>
    <layers>
      <iconSpec id="5ed6352b-1e52-4d11-8c9d-e398b2590ed8">
        <baseIcon>harddisk.png</baseIcon>
        <basePath>Operating System/</basePath>
        <readOnly>false</readOnly>
        <layers/>
      </iconSpec>
      <iconSpec id="6e681b52-b808-41f7-805b-a04271ea6b7a">
        <baseIcon>error.png</baseIcon>
        <basePath>Annotations/</basePath>
        <readOnly>false</readOnly>
        <layers/>
      </iconSpec>
    </layers>
  </iconSpec>
  <opRef>
    <refId>46c0f7ea-a981-4ddc-bcaf-d4faed7af0b6</refId>
  </opRef>
  <fieldValues/>
  <groupAliasRef>
    <refId>5233030c-af46-432b-a682-b326ca6bf2ae</refId>
    <refName>RAS_Operator_Path</refName>
  </groupAliasRef>
  <overrideGroupAlias>${overrideJRAS}</overrideGroupAlias>
</operation>